snetd_alpha/__init__.py
snetd_alpha/blockchain.py
snetd_alpha/configuration.py
snetd_alpha/daemon.py
snetd_alpha/resources/Agent.json
snetd_alpha-0.1.0.data/scripts/snetd
snetd_alpha-0.1.0.dist-info/METADATA
snetd_alpha-0.1.0.dist-info/RECORD
snetd_alpha-0.1.0.dist-info/WHEEL
snetd_alpha-0.1.0.dist-info/top_level.txt
